laser_image_faulting/__init__.py
laser_image_faulting/fault_detection.py
laser_image_faulting/pyarmor_runtime_000000/__init__.py
laser_image_faulting/pyarmor_runtime_000000/pyarmor_runtime.so
laser_image_faulting-0.0.25.dist-info/METADATA
laser_image_faulting-0.0.25.dist-info/WHEEL
laser_image_faulting-0.0.25.dist-info/RECORD
